[
  {
    "date": "2025-04-11",
    "stock": "515180",
    "name": "红利ETF易方达",
    "size": "716663.7",
    "scrapeTime": "2025-04-11T23:59:16.755Z"
  },
  {
    "date": "2025-04-10",
    "stock": "515180",
    "name": "红利ETF易方达",
    "size": "720263.7",
    "scrapeTime": "2025-04-11T23:59:16.755Z"
  },
  {
    "date": "2025-04-09",
    "stock": "515180",
    "name": "红利ETF易方达",
    "size": "723863.7",
    "scrapeTime": "2025-04-11T23:59:16.755Z"
  },
  {
    "date": "2025-04-08",
    "stock": "515180",
    "name": "红利ETF易方达",
    "size": "716263.7",
    "scrapeTime": "2025-04-11T23:59:16.754Z"
  },
  {
    "date": "2025-04-07",
    "stock": "515180",
    "name": "红利ETF易方达",
    "size": "715163.7",
    "scrapeTime": "2025-04-11T23:59:16.754Z"
  },
  {
    "date": "2025-04-03",
    "stock": "515180",
    "name": "红利ETF易方达",
    "size": "695963.7",
    "scrapeTime": "2025-04-11T23:59:16.754Z"
  },
  {
    "date": "2025-04-02",
    "stock": "515180",
    "name": "红利ETF易方达",
    "size": "695763.7",
    "scrapeTime": "2025-04-11T23:59:16.753Z"
  },
  {
    "date": "2025-04-01",
    "stock": "515180",
    "name": "红利ETF易方达",
    "size": "695963.7",
    "scrapeTime": "2025-04-11T23:59:16.753Z"
  },
  {
    "date": "2025-03-31",
    "stock": "515180",
    "name": "红利ETF易方达",
    "size": "695763.7",
    "scrapeTime": "2025-04-11T23:59:16.753Z"
  },
  {
    "date": "2025-03-28",
    "stock": "515180",
    "name": "红利ETF易方达",
    "size": "697963.7",
    "scrapeTime": "2025-04-11T23:59:16.752Z"
  }
]